metalogistic/__init__.py
metalogistic/main.py
metalogistic/support.py
metalogistic-0.0.12.dist-info/LICENSE
metalogistic-0.0.12.dist-info/METADATA
metalogistic-0.0.12.dist-info/WHEEL
metalogistic-0.0.12.dist-info/RECORD
