Metadata-Version: 2.1
Name: metalogistic
Version: 0.0.12
Summary: A Python package for the metalogistic distribution. The metalogistic or metalog distribution is a highly flexible probability distribution that can be used to model data without traditional parameters.
Home-page: https://github.com/tadamcz/metalogistic
License: GNU Affero General Public License v3
Author: Tom Adamczewski
Author-email: tadamczewskipublic@gmail.com
Requires-Python: >=3.8,<4.0
Classifier: License :: Other/Proprietary License
Classifier: Programming Language :: Python :: 3
Classifier: Programming Language :: Python :: 3.8
Classifier: Programming Language :: Python :: 3.9
Classifier: Programming Language :: Python :: 3.10
Classifier: Programming Language :: Python :: 3.11
Requires-Dist: matplotlib (>=3.5.1,<4.0.0)
Requires-Dist: numpy (>=1.22.3,<2.0.0)
Requires-Dist: scipy (>=1.8.0,<2.0.0)
Project-URL: Repository, https://github.com/tadamcz/metalogistic
